osre.libs/libboost_system-a9b7401f.so.1.80.0
osre.libs/libboost_serialization-5ca61c32.so.1.80.0
osre.libs/libboost_filesystem-bcc74335.so.1.80.0
osre.libs/libboost_timer-971599a0.so.1.80.0
osre.libs/libQuantLib-b0fd298c.so.1.28.0
osre.libs/libboost_date_time-83b253b6.so.1.80.0
osre.libs/libboost_thread-5ca2b49d.so.1.80.0
osre.libs/libboost_chrono-c36bb13e.so.1.80.0
osre.libs/libboost_iostreams-21556367.so.1.80.0
osre.libs/libOREAnalytics-2585c297.so
osre.libs/libboost_regex-4c6467d2.so.1.80.0
osre.libs/libOREData-056747b7.so
osre.libs/libQuantExt-f005d6ba.so
osre.libs/libboost_atomic-f6197b62.so.1.80.0
osre-1.8.9.0.dist-info/WHEEL
osre-1.8.9.0.dist-info/top_level.txt
osre-1.8.9.0.dist-info/RECORD
osre-1.8.9.0.dist-info/METADATA
OREAnalytics/_OREAnalytics.pypy39-pp73-x86_64-linux-gnu.so
OREAnalytics/__init__.py
OREAnalytics/OREAnalytics.py
